dbus_python_client_gen/__init__.py
dbus_python_client_gen/_errors.py
dbus_python_client_gen/_invokers.py
dbus_python_client_gen/_version.py
dbus_python_client_gen-0.8.4.dist-info/licenses/LICENSE
dbus_python_client_gen-0.8.4.dist-info/METADATA
dbus_python_client_gen-0.8.4.dist-info/WHEEL
dbus_python_client_gen-0.8.4.dist-info/top_level.txt
dbus_python_client_gen-0.8.4.dist-info/RECORD
