Metadata-Version: 2.4
Name: dbus-python-client-gen
Version: 0.8.4
Summary: transforms values into properly wrapped dbus-python objects
Home-page: https://github.com/stratis-storage/dbus-python-client-gen
Author: Anne Mulhern
Author-email: amulhern@redhat.com
License: MPL-2.0
Platform: Linux
Classifier: Development Status :: 4 - Beta
Classifier: Intended Audience :: Developers
Classifier: Operating System :: POSIX :: Linux
Classifier: Programming Language :: Python
Classifier: Programming Language :: Python :: 3
Classifier: Programming Language :: Python :: Implementation :: CPython
Classifier: Programming Language :: Python :: Implementation :: PyPy
Classifier: Topic :: Software Development :: Libraries
Classifier: Topic :: Software Development :: Libraries :: Python Modules
Requires-Python: >=3.12
License-File: LICENSE
Requires-Dist: dbus-python
Requires-Dist: into-dbus-python>=0.8
Dynamic: license-file
